Flask_PonyAPI-0.0.5.dist-info/METADATA
Flask_PonyAPI-0.0.5.dist-info/RECORD
Flask_PonyAPI-0.0.5.dist-info/WHEEL
Flask_PonyAPI-0.0.5.dist-info/top_level.txt
flask_ponyapi/__init__.py
flask_ponyapi/exceptions.py
flask_ponyapi/manager.py
flask_ponyapi/responses.py
